{
  "current_phase": 4,
  "completed_phases": [
    1,
    2,
    3,
    4
  ],
  "cumulative_mutations": {
    "flags.early_stall_exit": false,
    "param_overrides.early_stall_check_hours": 12,
    "param_overrides.early_stall_mfe_threshold": 0.2,
    "param_overrides.max_hold_hours": 88,
    "param_overrides.adx_on": 14,
    "param_overrides.recovery_tolerance_atr_trend": 0.55
  },
  "phase_results": {
    "1": {
      "focus": "Opportunity Surface",
      "base_mutations": {
        "flags.early_stall_exit": true,
        "param_overrides.early_stall_check_hours": 12,
        "param_overrides.early_stall_mfe_threshold": 0.2,
        "param_overrides.max_hold_hours": 80
      },
      "final_mutations": {
        "flags.early_stall_exit": true,
        "param_overrides.early_stall_check_hours": 12,
        "param_overrides.early_stall_mfe_threshold": 0.2,
        "param_overrides.max_hold_hours": 80,
        "param_overrides.adx_on": 14
      },
      "base_score": 0.6139069886062933,
      "final_score": 0.6299551004878143,
      "kept_features": [
        "adx_on_14"
      ],
      "rounds": [
        {
          "round_num": 1,
          "candidates_tested": 21,
          "best_name": "adx_on_14",
          "best_score": 0.6299551004878143,
          "best_delta_pct": 2.6140949979986083,
          "kept": true,
          "rejected_count": 2
        },
        {
          "round_num": 2,
          "candidates_tested": 14,
          "best_name": "confirm_days_0",
          "best_score": 0.6299551004878143,
          "best_delta_pct": 0.0,
          "kept": false,
          "rejected_count": 0
        }
      ],
      "final_metrics": {
        "total_trades": 275,
        "win_rate": 0.7890909090909091,
        "profit_factor": 5.394264158446627,
        "max_dd_pct": 0.021861988563815295,
        "calmar": 2.0925648083001064e-09,
        "sharpe": 1.6081208538368639,
        "net_return_pct": 26.442799999999334,
        "total_r": 215.15610307015595,
        "max_dd_r": 4.358149205547946,
        "calmar_r": 49.3686867802188,
        "avg_r": 0.7823858293460216,
        "mfe_capture": 0.6743261828992073,
        "trades_per_month": 4.742328392030969
      },
      "accepted_count": 1,
      "elapsed_seconds": 330.51885056495667,
      "suggested_experiments": [],
      "analysis": {
        "phase": 1,
        "goal_progress": {
          "total_r": {
            "target": 300.0,
            "actual": 215.15610307015595,
            "pct_of_target": 71.71870102338531
          },
          "profit_factor": {
            "target": 6.0,
            "actual": 5.394264158446627,
            "pct_of_target": 89.90440264077712
          },
          "max_dd_pct": {
            "target": 0.012,
            "actual": 0.021861988563815295,
            "pct_of_target": 54.88979177247265
          },
          "calmar_r": {
            "target": 60.0,
            "actual": 49.3686867802188,
            "pct_of_target": 82.281144633698
          },
          "total_trades": {
            "target": 400,
            "actual": 275.0,
            "pct_of_target": 68.75
          },
          "mfe_capture": {
            "target": 0.8,
            "actual": 0.6743261828992073,
            "pct_of_target": 84.29077286240091
          },
          "win_rate": {
            "target": 0.85,
            "actual": 0.7890909090909091,
            "pct_of_target": 92.83422459893048
          },
          "trades_per_month": {
            "target": 7.5,
            "actual": 4.742328392030969,
            "pct_of_target": 63.23104522707958
          }
        },
        "strengths": [
          "profit_factor: 5.3943 (90% of 6.0000)",
          "calmar_r: 49.3687 (82% of 60.0000)",
          "mfe_capture: 0.6743 (84% of 0.8000)",
          "win_rate: 0.7891 (93% of 0.8500)"
        ],
        "weaknesses": [
          "max_dd_pct: 0.0219 (55% of 0.0120)"
        ],
        "scoring_assessment": "EFFECTIVE",
        "diagnostic_gaps": [],
        "suggested_experiments": [],
        "recommendation": "advance",
        "recommendation_reason": "Gate passed.",
        "report": "======================================================================\nPHASE 1 ANALYSIS\n======================================================================\n\nRecommendation: advance\nReason: Gate passed.\nScoring assessment: EFFECTIVE\n\nStrengths:\n  + profit_factor: 5.3943 (90% of 6.0000)\n  + calmar_r: 49.3687 (82% of 60.0000)\n  + mfe_capture: 0.6743 (84% of 0.8000)\n  + win_rate: 0.7891 (93% of 0.8500)\n\nWeaknesses:\n  - max_dd_pct: 0.0219 (55% of 0.0120)\n\nGoal Progress:\n  total_r: 215.1561 / 300.0000 (72%)\n  profit_factor: 5.3943 / 6.0000 (90%)\n  max_dd_pct: 0.0219 / 0.0120 (55%)\n  calmar_r: 49.3687 / 60.0000 (82%)\n  total_trades: 275.0000 / 400.0000 (69%)\n  mfe_capture: 0.6743 / 0.8000 (84%)\n  win_rate: 0.7891 / 0.8500 (93%)\n  trades_per_month: 4.7423 / 7.5000 (63%)",
        "scoring_weight_overrides": null,
        "extra": {}
      },
      "new_mutations": {
        "param_overrides.adx_on": 14
      },
      "applied_phase_mutations": true,
      "attempted_final_mutations": {
        "flags.early_stall_exit": true,
        "param_overrides.early_stall_check_hours": 12,
        "param_overrides.early_stall_mfe_threshold": 0.2,
        "param_overrides.max_hold_hours": 80,
        "param_overrides.adx_on": 14
      },
      "attempted_final_score": 0.6299551004878143,
      "attempted_final_metrics": {
        "total_trades": 275,
        "win_rate": 0.7890909090909091,
        "profit_factor": 5.394264158446627,
        "max_dd_pct": 0.021861988563815295,
        "calmar": 2.0925648083001064e-09,
        "sharpe": 1.6081208538368639,
        "net_return_pct": 26.442799999999334,
        "total_r": 215.15610307015595,
        "max_dd_r": 4.358149205547946,
        "calmar_r": 49.3686867802188,
        "avg_r": 0.7823858293460216,
        "mfe_capture": 0.6743261828992073,
        "trades_per_month": 4.742328392030969
      },
      "attempted_kept_features": [
        "adx_on_14"
      ],
      "attempted_accepted_count": 1
    },
    "2": {
      "focus": "Signal Geometry",
      "base_mutations": {
        "flags.early_stall_exit": true,
        "param_overrides.early_stall_check_hours": 12,
        "param_overrides.early_stall_mfe_threshold": 0.2,
        "param_overrides.max_hold_hours": 80,
        "param_overrides.adx_on": 14
      },
      "final_mutations": {
        "flags.early_stall_exit": true,
        "param_overrides.early_stall_check_hours": 12,
        "param_overrides.early_stall_mfe_threshold": 0.2,
        "param_overrides.max_hold_hours": 80,
        "param_overrides.adx_on": 14,
        "param_overrides.recovery_tolerance_atr_trend": 0.55
      },
      "base_score": 0.6299551004878143,
      "final_score": 0.6644083101664948,
      "kept_features": [
        "recov_trend_055"
      ],
      "rounds": [
        {
          "round_num": 1,
          "candidates_tested": 27,
          "best_name": "recov_trend_055",
          "best_score": 0.6644083101664948,
          "best_delta_pct": 5.469153222507631,
          "kept": true,
          "rejected_count": 1
        },
        {
          "round_num": 2,
          "candidates_tested": 22,
          "best_name": "ema_pull_strong_50",
          "best_score": 0.6645363027550469,
          "best_delta_pct": 0.019264146247665585,
          "kept": false,
          "rejected_count": 0
        }
      ],
      "final_metrics": {
        "total_trades": 295,
        "win_rate": 0.7898305084745763,
        "profit_factor": 5.354441648960329,
        "max_dd_pct": 0.020111668455316176,
        "calmar": 2.2799472498527545e-09,
        "sharpe": 1.6305741047464863,
        "net_return_pct": 26.511499999999305,
        "total_r": 224.29160797698333,
        "max_dd_r": 3.4024611131238913,
        "calmar_r": 65.92040306114039,
        "avg_r": 0.7603105355151977,
        "mfe_capture": 0.6795240856675294,
        "trades_per_month": 5.087225002360495
      },
      "accepted_count": 1,
      "elapsed_seconds": 470.61351227760315,
      "suggested_experiments": [],
      "analysis": {
        "phase": 2,
        "goal_progress": {
          "total_r": {
            "target": 300.0,
            "actual": 224.29160797698333,
            "pct_of_target": 74.76386932566112
          },
          "profit_factor": {
            "target": 6.0,
            "actual": 5.354441648960329,
            "pct_of_target": 89.24069414933881
          },
          "max_dd_pct": {
            "target": 0.012,
            "actual": 0.020111668455316176,
            "pct_of_target": 59.66685472496442
          },
          "calmar_r": {
            "target": 60.0,
            "actual": 65.92040306114039,
            "pct_of_target": 109.86733843523398
          },
          "total_trades": {
            "target": 400,
            "actual": 295.0,
            "pct_of_target": 73.75
          },
          "mfe_capture": {
            "target": 0.8,
            "actual": 0.6795240856675294,
            "pct_of_target": 84.94051070844118
          },
          "win_rate": {
            "target": 0.85,
            "actual": 0.7898305084745763,
            "pct_of_target": 92.92123629112662
          },
          "trades_per_month": {
            "target": 7.5,
            "actual": 5.087225002360495,
            "pct_of_target": 67.82966669813993
          }
        },
        "strengths": [
          "profit_factor: 5.3544 (89% of 6.0000)",
          "calmar_r: 65.9204 (110% of 60.0000)",
          "mfe_capture: 0.6795 (85% of 0.8000)",
          "win_rate: 0.7898 (93% of 0.8500)"
        ],
        "weaknesses": [
          "max_dd_pct: 0.0201 (60% of 0.0120)"
        ],
        "scoring_assessment": "EFFECTIVE",
        "diagnostic_gaps": [],
        "suggested_experiments": [],
        "recommendation": "advance",
        "recommendation_reason": "Gate passed.",
        "report": "======================================================================\nPHASE 2 ANALYSIS\n======================================================================\n\nRecommendation: advance\nReason: Gate passed.\nScoring assessment: EFFECTIVE\n\nStrengths:\n  + profit_factor: 5.3544 (89% of 6.0000)\n  + calmar_r: 65.9204 (110% of 60.0000)\n  + mfe_capture: 0.6795 (85% of 0.8000)\n  + win_rate: 0.7898 (93% of 0.8500)\n\nWeaknesses:\n  - max_dd_pct: 0.0201 (60% of 0.0120)\n\nGoal Progress:\n  total_r: 224.2916 / 300.0000 (75%)\n  profit_factor: 5.3544 / 6.0000 (89%)\n  max_dd_pct: 0.0201 / 0.0120 (60%)\n  calmar_r: 65.9204 / 60.0000 (110%)\n  total_trades: 295.0000 / 400.0000 (74%)\n  mfe_capture: 0.6795 / 0.8000 (85%)\n  win_rate: 0.7898 / 0.8500 (93%)\n  trades_per_month: 5.0872 / 7.5000 (68%)",
        "scoring_weight_overrides": null,
        "extra": {}
      },
      "new_mutations": {
        "param_overrides.recovery_tolerance_atr_trend": 0.55
      },
      "applied_phase_mutations": true,
      "attempted_final_mutations": {
        "flags.early_stall_exit": true,
        "param_overrides.early_stall_check_hours": 12,
        "param_overrides.early_stall_mfe_threshold": 0.2,
        "param_overrides.max_hold_hours": 80,
        "param_overrides.adx_on": 14,
        "param_overrides.recovery_tolerance_atr_trend": 0.55
      },
      "attempted_final_score": 0.6644083101664948,
      "attempted_final_metrics": {
        "total_trades": 295,
        "win_rate": 0.7898305084745763,
        "profit_factor": 5.354441648960329,
        "max_dd_pct": 0.020111668455316176,
        "calmar": 2.2799472498527545e-09,
        "sharpe": 1.6305741047464863,
        "net_return_pct": 26.511499999999305,
        "total_r": 224.29160797698333,
        "max_dd_r": 3.4024611131238913,
        "calmar_r": 65.92040306114039,
        "avg_r": 0.7603105355151977,
        "mfe_capture": 0.6795240856675294,
        "trades_per_month": 5.087225002360495
      },
      "attempted_kept_features": [
        "recov_trend_055"
      ],
      "attempted_accepted_count": 1
    },
    "3": {
      "focus": "Execution & Stops",
      "base_mutations": {
        "flags.early_stall_exit": true,
        "param_overrides.early_stall_check_hours": 12,
        "param_overrides.early_stall_mfe_threshold": 0.2,
        "param_overrides.max_hold_hours": 80,
        "param_overrides.adx_on": 14,
        "param_overrides.recovery_tolerance_atr_trend": 0.55
      },
      "final_mutations": {
        "flags.early_stall_exit": true,
        "param_overrides.early_stall_check_hours": 12,
        "param_overrides.early_stall_mfe_threshold": 0.2,
        "param_overrides.max_hold_hours": 80,
        "param_overrides.adx_on": 14,
        "param_overrides.recovery_tolerance_atr_trend": 0.55
      },
      "base_score": 0.6644083101664948,
      "final_score": 0.6644083101664948,
      "kept_features": [],
      "rounds": [
        {
          "round_num": 1,
          "candidates_tested": 19,
          "best_name": "expiry_6h",
          "best_score": 0.6644083101664948,
          "best_delta_pct": 0.0,
          "kept": false,
          "rejected_count": 4
        }
      ],
      "final_metrics": {
        "total_trades": 295,
        "win_rate": 0.7898305084745763,
        "profit_factor": 5.354441648960329,
        "max_dd_pct": 0.020111668455316176,
        "calmar": 2.2799472498527545e-09,
        "sharpe": 1.6305741047464863,
        "net_return_pct": 26.511499999999305,
        "total_r": 224.29160797698333,
        "max_dd_r": 3.4024611131238913,
        "calmar_r": 65.92040306114039,
        "avg_r": 0.7603105355151977,
        "mfe_capture": 0.6795240856675294,
        "trades_per_month": 5.087225002360495
      },
      "accepted_count": 0,
      "elapsed_seconds": 270.33702206611633,
      "suggested_experiments": [],
      "analysis": {
        "phase": 3,
        "goal_progress": {
          "total_r": {
            "target": 300.0,
            "actual": 224.29160797698333,
            "pct_of_target": 74.76386932566112
          },
          "profit_factor": {
            "target": 6.0,
            "actual": 5.354441648960329,
            "pct_of_target": 89.24069414933881
          },
          "max_dd_pct": {
            "target": 0.012,
            "actual": 0.020111668455316176,
            "pct_of_target": 59.66685472496442
          },
          "calmar_r": {
            "target": 60.0,
            "actual": 65.92040306114039,
            "pct_of_target": 109.86733843523398
          },
          "total_trades": {
            "target": 400,
            "actual": 295.0,
            "pct_of_target": 73.75
          },
          "mfe_capture": {
            "target": 0.8,
            "actual": 0.6795240856675294,
            "pct_of_target": 84.94051070844118
          },
          "win_rate": {
            "target": 0.85,
            "actual": 0.7898305084745763,
            "pct_of_target": 92.92123629112662
          },
          "trades_per_month": {
            "target": 7.5,
            "actual": 5.087225002360495,
            "pct_of_target": 67.82966669813993
          }
        },
        "strengths": [
          "profit_factor: 5.3544 (89% of 6.0000)",
          "calmar_r: 65.9204 (110% of 60.0000)",
          "mfe_capture: 0.6795 (85% of 0.8000)",
          "win_rate: 0.7898 (93% of 0.8500)"
        ],
        "weaknesses": [
          "max_dd_pct: 0.0201 (60% of 0.0120)"
        ],
        "scoring_assessment": "EFFECTIVE",
        "diagnostic_gaps": [],
        "suggested_experiments": [],
        "recommendation": "advance",
        "recommendation_reason": "Gate passed.",
        "report": "======================================================================\nPHASE 3 ANALYSIS\n======================================================================\n\nRecommendation: advance\nReason: Gate passed.\nScoring assessment: EFFECTIVE\n\nStrengths:\n  + profit_factor: 5.3544 (89% of 6.0000)\n  + calmar_r: 65.9204 (110% of 60.0000)\n  + mfe_capture: 0.6795 (85% of 0.8000)\n  + win_rate: 0.7898 (93% of 0.8500)\n\nWeaknesses:\n  - max_dd_pct: 0.0201 (60% of 0.0120)\n\nGoal Progress:\n  total_r: 224.2916 / 300.0000 (75%)\n  profit_factor: 5.3544 / 6.0000 (89%)\n  max_dd_pct: 0.0201 / 0.0120 (60%)\n  calmar_r: 65.9204 / 60.0000 (110%)\n  total_trades: 295.0000 / 400.0000 (74%)\n  mfe_capture: 0.6795 / 0.8000 (85%)\n  win_rate: 0.7898 / 0.8500 (93%)\n  trades_per_month: 5.0872 / 7.5000 (68%)",
        "scoring_weight_overrides": null,
        "extra": {}
      },
      "new_mutations": {},
      "applied_phase_mutations": true,
      "attempted_final_mutations": {
        "flags.early_stall_exit": true,
        "param_overrides.early_stall_check_hours": 12,
        "param_overrides.early_stall_mfe_threshold": 0.2,
        "param_overrides.max_hold_hours": 80,
        "param_overrides.adx_on": 14,
        "param_overrides.recovery_tolerance_atr_trend": 0.55
      },
      "attempted_final_score": 0.6644083101664948,
      "attempted_final_metrics": {
        "total_trades": 295,
        "win_rate": 0.7898305084745763,
        "profit_factor": 5.354441648960329,
        "max_dd_pct": 0.020111668455316176,
        "calmar": 2.2799472498527545e-09,
        "sharpe": 1.6305741047464863,
        "net_return_pct": 26.511499999999305,
        "total_r": 224.29160797698333,
        "max_dd_r": 3.4024611131238913,
        "calmar_r": 65.92040306114039,
        "avg_r": 0.7603105355151977,
        "mfe_capture": 0.6795240856675294,
        "trades_per_month": 5.087225002360495
      },
      "attempted_kept_features": [],
      "attempted_accepted_count": 0
    },
    "4": {
      "focus": "Exits, Add-ons & Allocation",
      "base_mutations": {
        "flags.early_stall_exit": true,
        "param_overrides.early_stall_check_hours": 12,
        "param_overrides.early_stall_mfe_threshold": 0.2,
        "param_overrides.max_hold_hours": 80,
        "param_overrides.adx_on": 14,
        "param_overrides.recovery_tolerance_atr_trend": 0.55
      },
      "final_mutations": {
        "flags.early_stall_exit": false,
        "param_overrides.early_stall_check_hours": 12,
        "param_overrides.early_stall_mfe_threshold": 0.2,
        "param_overrides.max_hold_hours": 88,
        "param_overrides.adx_on": 14,
        "param_overrides.recovery_tolerance_atr_trend": 0.55
      },
      "base_score": 0.6644083101664948,
      "final_score": 0.6824708002450192,
      "kept_features": [
        "disable_early_stall",
        "max_hold_hours_plus10"
      ],
      "rounds": [
        {
          "round_num": 1,
          "candidates_tested": 47,
          "best_name": "disable_early_stall",
          "best_score": 0.6725889048174586,
          "best_delta_pct": 1.2312601341355565,
          "kept": true,
          "rejected_count": 5
        },
        {
          "round_num": 2,
          "candidates_tested": 34,
          "best_name": "max_hold_hours_plus10",
          "best_score": 0.6824708002450192,
          "best_delta_pct": 1.4692325961342658,
          "kept": true,
          "rejected_count": 0
        },
        {
          "round_num": 3,
          "candidates_tested": 32,
          "best_name": "tp1_frac_050",
          "best_score": 0.6840892976572005,
          "best_delta_pct": 0.23715262420022537,
          "kept": false,
          "rejected_count": 0
        }
      ],
      "final_metrics": {
        "total_trades": 276,
        "win_rate": 0.8333333333333334,
        "profit_factor": 5.933601160097628,
        "max_dd_pct": 0.02313828858709008,
        "calmar": 2.0147575990307146e-09,
        "sharpe": 1.5880250114001593,
        "net_return_pct": 27.008499999999273,
        "total_r": 228.70458501422866,
        "max_dd_r": 3.004501929450427,
        "calmar_r": 76.12063176676425,
        "avg_r": 0.8286398007761908,
        "mfe_capture": 0.6786340877233751,
        "trades_per_month": 4.759573222547446
      },
      "accepted_count": 2,
      "elapsed_seconds": 1075.87158370018,
      "suggested_experiments": [],
      "analysis": {
        "phase": 4,
        "goal_progress": {
          "total_r": {
            "target": 300.0,
            "actual": 228.70458501422866,
            "pct_of_target": 76.23486167140955
          },
          "profit_factor": {
            "target": 6.0,
            "actual": 5.933601160097628,
            "pct_of_target": 98.8933526682938
          },
          "max_dd_pct": {
            "target": 0.012,
            "actual": 0.02313828858709008,
            "pct_of_target": 51.862089777440815
          },
          "calmar_r": {
            "target": 60.0,
            "actual": 76.12063176676425,
            "pct_of_target": 126.86771961127374
          },
          "total_trades": {
            "target": 400,
            "actual": 276.0,
            "pct_of_target": 69.0
          },
          "mfe_capture": {
            "target": 0.8,
            "actual": 0.6786340877233751,
            "pct_of_target": 84.82926096542188
          },
          "win_rate": {
            "target": 0.85,
            "actual": 0.8333333333333334,
            "pct_of_target": 98.03921568627452
          },
          "trades_per_month": {
            "target": 7.5,
            "actual": 4.759573222547446,
            "pct_of_target": 63.46097630063261
          }
        },
        "strengths": [
          "profit_factor: 5.9336 (99% of 6.0000)",
          "calmar_r: 76.1206 (127% of 60.0000)",
          "mfe_capture: 0.6786 (85% of 0.8000)",
          "win_rate: 0.8333 (98% of 0.8500)"
        ],
        "weaknesses": [
          "max_dd_pct: 0.0231 (52% of 0.0120)"
        ],
        "scoring_assessment": "EFFECTIVE",
        "diagnostic_gaps": [],
        "suggested_experiments": [],
        "recommendation": "advance",
        "recommendation_reason": "Gate passed.",
        "report": "======================================================================\nPHASE 4 ANALYSIS\n======================================================================\n\nRecommendation: advance\nReason: Gate passed.\nScoring assessment: EFFECTIVE\n\nStrengths:\n  + profit_factor: 5.9336 (99% of 6.0000)\n  + calmar_r: 76.1206 (127% of 60.0000)\n  + mfe_capture: 0.6786 (85% of 0.8000)\n  + win_rate: 0.8333 (98% of 0.8500)\n\nWeaknesses:\n  - max_dd_pct: 0.0231 (52% of 0.0120)\n\nGoal Progress:\n  total_r: 228.7046 / 300.0000 (76%)\n  profit_factor: 5.9336 / 6.0000 (99%)\n  max_dd_pct: 0.0231 / 0.0120 (52%)\n  calmar_r: 76.1206 / 60.0000 (127%)\n  total_trades: 276.0000 / 400.0000 (69%)\n  mfe_capture: 0.6786 / 0.8000 (85%)\n  win_rate: 0.8333 / 0.8500 (98%)\n  trades_per_month: 4.7596 / 7.5000 (63%)",
        "scoring_weight_overrides": null,
        "extra": {}
      },
      "new_mutations": {
        "flags.early_stall_exit": false,
        "param_overrides.max_hold_hours": 88
      },
      "applied_phase_mutations": true,
      "attempted_final_mutations": {
        "flags.early_stall_exit": false,
        "param_overrides.early_stall_check_hours": 12,
        "param_overrides.early_stall_mfe_threshold": 0.2,
        "param_overrides.max_hold_hours": 88,
        "param_overrides.adx_on": 14,
        "param_overrides.recovery_tolerance_atr_trend": 0.55
      },
      "attempted_final_score": 0.6824708002450192,
      "attempted_final_metrics": {
        "total_trades": 276,
        "win_rate": 0.8333333333333334,
        "profit_factor": 5.933601160097628,
        "max_dd_pct": 0.02313828858709008,
        "calmar": 2.0147575990307146e-09,
        "sharpe": 1.5880250114001593,
        "net_return_pct": 27.008499999999273,
        "total_r": 228.70458501422866,
        "max_dd_r": 3.004501929450427,
        "calmar_r": 76.12063176676425,
        "avg_r": 0.8286398007761908,
        "mfe_capture": 0.6786340877233751,
        "trades_per_month": 4.759573222547446
      },
      "attempted_kept_features": [
        "disable_early_stall",
        "max_hold_hours_plus10"
      ],
      "attempted_accepted_count": 2
    }
  },
  "phase_gate_results": {
    "1": {
      "passed": true,
      "criteria": [
        {
          "name": "hard_min_trades",
          "target": 220.0,
          "actual": 275.0,
          "passed": true
        },
        {
          "name": "hard_max_dd_pct",
          "target": 0.06,
          "actual": 0.021861988563815295,
          "passed": true
        },
        {
          "name": "hard_min_pf",
          "target": 1.8,
          "actual": 5.394264158446627,
          "passed": true
        },
        {
          "name": "hard_min_wr",
          "target": 0.58,
          "actual": 0.7890909090909091,
          "passed": true
        },
        {
          "name": "total_trades",
          "target": 250.0,
          "actual": 275.0,
          "passed": true
        },
        {
          "name": "trades_per_month",
          "target": 4.5,
          "actual": 4.742328392030969,
          "passed": true
        },
        {
          "name": "total_r",
          "target": 190.0,
          "actual": 215.15610307015595,
          "passed": true
        }
      ],
      "failure_category": null,
      "recommendations": []
    },
    "2": {
      "passed": true,
      "criteria": [
        {
          "name": "hard_min_trades",
          "target": 220.0,
          "actual": 295.0,
          "passed": true
        },
        {
          "name": "hard_max_dd_pct",
          "target": 0.06,
          "actual": 0.020111668455316176,
          "passed": true
        },
        {
          "name": "hard_min_pf",
          "target": 1.8,
          "actual": 5.354441648960329,
          "passed": true
        },
        {
          "name": "hard_min_wr",
          "target": 0.58,
          "actual": 0.7898305084745763,
          "passed": true
        },
        {
          "name": "total_trades",
          "target": 255.0,
          "actual": 295.0,
          "passed": true
        },
        {
          "name": "win_rate",
          "target": 0.68,
          "actual": 0.7898305084745763,
          "passed": true
        },
        {
          "name": "profit_factor",
          "target": 2.5,
          "actual": 5.354441648960329,
          "passed": true
        }
      ],
      "failure_category": null,
      "recommendations": []
    },
    "3": {
      "passed": true,
      "criteria": [
        {
          "name": "hard_min_trades",
          "target": 220.0,
          "actual": 295.0,
          "passed": true
        },
        {
          "name": "hard_max_dd_pct",
          "target": 0.06,
          "actual": 0.020111668455316176,
          "passed": true
        },
        {
          "name": "hard_min_pf",
          "target": 1.8,
          "actual": 5.354441648960329,
          "passed": true
        },
        {
          "name": "hard_min_wr",
          "target": 0.58,
          "actual": 0.7898305084745763,
          "passed": true
        },
        {
          "name": "trades_per_month",
          "target": 4.7,
          "actual": 5.087225002360495,
          "passed": true
        },
        {
          "name": "total_trades",
          "target": 260.0,
          "actual": 295.0,
          "passed": true
        },
        {
          "name": "profit_factor",
          "target": 2.8,
          "actual": 5.354441648960329,
          "passed": true
        }
      ],
      "failure_category": null,
      "recommendations": []
    },
    "4": {
      "passed": true,
      "criteria": [
        {
          "name": "hard_min_trades",
          "target": 220.0,
          "actual": 276.0,
          "passed": true
        },
        {
          "name": "hard_max_dd_pct",
          "target": 0.06,
          "actual": 0.02313828858709008,
          "passed": true
        },
        {
          "name": "hard_min_pf",
          "target": 1.8,
          "actual": 5.933601160097628,
          "passed": true
        },
        {
          "name": "hard_min_wr",
          "target": 0.58,
          "actual": 0.8333333333333334,
          "passed": true
        },
        {
          "name": "calmar_r",
          "target": 35.0,
          "actual": 76.12063176676425,
          "passed": true
        },
        {
          "name": "total_r",
          "target": 200.0,
          "actual": 228.70458501422866,
          "passed": true
        },
        {
          "name": "sharpe",
          "target": 1.0,
          "actual": 1.5880250114001593,
          "passed": true
        },
        {
          "name": "no_regress_profit_factor",
          "target": 5.086719566512312,
          "actual": 5.933601160097628,
          "passed": true
        },
        {
          "name": "no_regress_total_r",
          "target": 213.07702757813416,
          "actual": 228.70458501422866,
          "passed": true
        },
        {
          "name": "no_regress_win_rate",
          "target": 0.7503389830508475,
          "actual": 0.8333333333333334,
          "passed": true
        },
        {
          "name": "no_regress_calmar_r",
          "target": 62.62438290808337,
          "actual": 76.12063176676425,
          "passed": true
        }
      ],
      "failure_category": null,
      "recommendations": []
    }
  },
  "retry_count": {},
  "scoring_retries": {},
  "diagnostic_retries": {},
  "phase_timestamps": {
    "1": {
      "started": "2026-04-30T12:35:09.823377+00:00",
      "completed": "2026-04-30T12:40:43.499014+00:00"
    },
    "2": {
      "started": "2026-04-30T12:40:43.523711+00:00",
      "completed": "2026-04-30T12:48:34.307909+00:00"
    },
    "3": {
      "started": "2026-04-30T12:48:34.347591+00:00",
      "completed": "2026-04-30T12:53:04.829822+00:00"
    },
    "4": {
      "started": "2026-04-30T12:53:04.853997+00:00",
      "completed": "2026-04-30T13:11:00.901561+00:00"
    }
  },
  "round_name": ""
}