{
  "generated_at_utc": "2026-05-06T16:03:59.105327+00:00",
  "output_dir": "C:\\Users\\sehyu\\Documents\\Other\\Projects\\trading\\backtests\\output\\swing\\tpc\\round_6\\alpha_audit_20260506_160248",
  "train_end": "2025-11-01",
  "oos_warmup_15m": 76047,
  "elapsed_minutes": 1.173387356599172,
  "metrics": {
    "train": {
      "headline": {
        "total_trades": 126.0,
        "net_return_pct": 96.90008999999951,
        "net_return_per_month": 1.753017100243309,
        "total_pnl_dollars": 96900.0899999974,
        "pnl_per_trade": 769.0483333333127,
        "profit_factor": 4.50784753872818,
        "dollar_profit_factor": 1.7673919239558589,
        "avg_r": 2.3525178578614763,
        "total_r": 296.417250090546,
        "r_per_month": 5.362477044302305,
        "win_rate": 0.5317460317460317,
        "max_dd_pct": 13.751244374781338,
        "sharpe": 0.711837065214622,
        "trades_per_month": 2.2794628429205592,
        "expectancy_frequency": 3.5518055984377015,
        "mfe_capture": 0.3062410277787097,
        "avg_mfe_r": 7.122903607351447,
        "avg_mae_r": 1.0774077692162312,
        "excellent_trades": 64.0,
        "excellent_trades_per_month": 1.1578223964040937,
        "excellent_rate": 0.5079365079365079,
        "two_r_plus_rate": 0.38095238095238093,
        "never_worked_rate": 0.30158730158730157,
        "false_positive_never_worked_rate": 0.30158730158730157,
        "low_mfe_loss_rate": 0.40476190476190477,
        "false_positive_low_mfe_loss_rate": 0.40476190476190477,
        "half_to_one_r_loss_rate": 0.10317460317460317,
        "right_then_lost_rate": 0.06349206349206349,
        "top5_winner_share": 0.7785939174023018,
        "dollar_top5_winner_share": 0.30447323916802216,
        "max_symbol_trade_share": 0.8412698412698413,
        "dominant_symbol_trade_share": 0.8412698412698413,
        "gld_trade_count": 106.0,
        "qqq_trade_count": 20.0,
        "gld_excellent_trades": 50.0,
        "qqq_excellent_trades": 14.0,
        "gld_excellent_rate": 0.4716981132075472,
        "qqq_excellent_rate": 0.7,
        "gld_trade_share": 0.8412698412698413,
        "max_gld_trade_share": 0.8412698412698413,
        "qqq_trade_share": 0.15873015873015872,
        "entry_requests": 128.0,
        "request_fill_rate": 0.984375,
        "order_terminal_rate": 0.015625,
        "worst_symbol_avg_r": 0.6540577803433286,
        "worst_year_avg_r": -0.8880217150007685,
        "worst_symbol_pnl": 44172.69000000057,
        "worst_symbol_pnl_pct": 44.17269000000057,
        "worst_year_pnl": -4070.8200000003612,
        "worst_year_pnl_pct": -4.070820000000362
      },
      "with_cohorts": {
        "total_trades": 126.0,
        "net_return_pct": 96.90008999999951,
        "net_return_per_month": 1.753017100243309,
        "total_pnl_dollars": 96900.0899999974,
        "pnl_per_trade": 769.0483333333127,
        "profit_factor": 4.50784753872818,
        "dollar_profit_factor": 1.7673919239558589,
        "avg_r": 2.3525178578614763,
        "total_r": 296.417250090546,
        "r_per_month": 5.362477044302305,
        "win_rate": 0.5317460317460317,
        "max_dd_pct": 13.751244374781338,
        "sharpe": 0.711837065214622,
        "trades_per_month": 2.2794628429205592,
        "expectancy_frequency": 3.5518055984377015,
        "mfe_capture": 0.3062410277787097,
        "avg_mfe_r": 7.122903607351447,
        "avg_mae_r": 1.0774077692162312,
        "excellent_trades": 64.0,
        "excellent_trades_per_month": 1.1578223964040937,
        "excellent_rate": 0.5079365079365079,
        "two_r_plus_rate": 0.38095238095238093,
        "never_worked_rate": 0.30158730158730157,
        "false_positive_never_worked_rate": 0.30158730158730157,
        "low_mfe_loss_rate": 0.40476190476190477,
        "false_positive_low_mfe_loss_rate": 0.40476190476190477,
        "half_to_one_r_loss_rate": 0.10317460317460317,
        "right_then_lost_rate": 0.06349206349206349,
        "top5_winner_share": 0.7785939174023018,
        "dollar_top5_winner_share": 0.30447323916802216,
        "max_symbol_trade_share": 0.8412698412698413,
        "dominant_symbol_trade_share": 0.8412698412698413,
        "gld_trade_count": 106.0,
        "qqq_trade_count": 20.0,
        "gld_excellent_trades": 50.0,
        "qqq_excellent_trades": 14.0,
        "gld_excellent_rate": 0.4716981132075472,
        "qqq_excellent_rate": 0.7,
        "gld_trade_share": 0.8412698412698413,
        "max_gld_trade_share": 0.8412698412698413,
        "qqq_trade_share": 0.15873015873015872,
        "entry_requests": 128.0,
        "request_fill_rate": 0.984375,
        "order_terminal_rate": 0.015625,
        "worst_symbol_avg_r": 0.6540577803433286,
        "worst_year_avg_r": -0.8880217150007685,
        "worst_symbol_pnl": 44172.69000000057,
        "worst_symbol_pnl_pct": 44.17269000000057,
        "worst_year_pnl": -4070.8200000003612,
        "worst_year_pnl_pct": -4.070820000000362,
        "cohorts": {
          "LONG": {
            "n": 75.0,
            "pnl": 76609.48999999891,
            "avg_r": 3.6874725701502395,
            "win_rate": 0.5333333333333333,
            "low_mfe_loss_rate": 0.4266666666666667
          },
          "SHORT": {
            "n": 51.0,
            "pnl": 20290.599999998507,
            "avg_r": 0.3893491633191763,
            "win_rate": 0.5294117647058824,
            "low_mfe_loss_rate": 0.37254901960784315
          },
          "GLD": {
            "n": 106.0,
            "pnl": 52727.399999996844,
            "avg_r": 2.6729820234309387,
            "win_rate": 0.5,
            "low_mfe_loss_rate": 0.42452830188679247
          },
          "QQQ": {
            "n": 20.0,
            "pnl": 44172.69000000057,
            "avg_r": 0.6540577803433286,
            "win_rate": 0.7,
            "low_mfe_loss_rate": 0.3
          }
        },
        "worst_trades": [
          {
            "symbol": "GLD",
            "direction": "LONG",
            "entry_time": "2024-06-24 20:15:00",
            "exit_time": "2024-06-25 08:00:00",
            "r": -3.003660884327733,
            "pnl": -5786.880000000104,
            "mfe_r": 0.5944745500231794,
            "mae_r": 2.972372750115986,
            "entry_type": "classic_38_62",
            "exit_reason": "STOP",
            "score": 16.0,
            "grade": "valid"
          },
          {
            "symbol": "GLD",
            "direction": "SHORT",
            "entry_time": "2025-06-20 13:00:00",
            "exit_time": "2025-06-20 13:15:00",
            "r": -1.410662763204799,
            "pnl": -4559.720000000121,
            "mfe_r": 0.0,
            "mae_r": 2.1816063663515237,
            "entry_type": "classic_38_62",
            "exit_reason": "STOP",
            "score": 16.0,
            "grade": "valid"
          },
          {
            "symbol": "GLD",
            "direction": "SHORT",
            "entry_time": "2022-11-21 14:45:00",
            "exit_time": "2022-11-22 10:30:00",
            "r": -1.212597388164979,
            "pnl": -4353.840000000047,
            "mfe_r": 1.2125973881649639,
            "mae_r": 1.1620724969914216,
            "entry_type": "classic_38_62",
            "exit_reason": "STOP",
            "score": 18.0,
            "grade": "valid"
          },
          {
            "symbol": "QQQ",
            "direction": "LONG",
            "entry_time": "2025-01-06 15:00:00",
            "exit_time": "2025-01-06 18:00:00",
            "r": -1.0215463744583322,
            "pnl": -4329.599999999924,
            "mfe_r": 0.5581131411674911,
            "mae_r": 1.2906366389497772,
            "entry_type": "classic_38_62",
            "exit_reason": "STOP",
            "score": 18.0,
            "grade": "valid"
          },
          {
            "symbol": "GLD",
            "direction": "LONG",
            "entry_time": "2023-07-05 13:30:00",
            "exit_time": "2023-07-05 13:45:00",
            "r": -2.028902710615495,
            "pnl": -3965.7600000000925,
            "mfe_r": 0.0,
            "mae_r": 2.7449860202444767,
            "entry_type": "classic_38_62",
            "exit_reason": "STOP",
            "score": 16.0,
            "grade": "valid"
          },
          {
            "symbol": "GLD",
            "direction": "SHORT",
            "entry_time": "2025-10-22 12:30:00",
            "exit_time": "2025-10-22 13:00:00",
            "r": -1.0352351267282867,
            "pnl": -3734.0400000001096,
            "mfe_r": 1.6777948605595838,
            "mae_r": 2.02584804971826,
            "entry_type": "classic_38_62",
            "exit_reason": "STOP",
            "score": 15.0,
            "grade": "valid"
          },
          {
            "symbol": "GLD",
            "direction": "SHORT",
            "entry_time": "2024-09-03 14:15:00",
            "exit_time": "2024-09-03 15:45:00",
            "r": -1.0580972149760413,
            "pnl": -3602.3400000000265,
            "mfe_r": 0.6046269799863278,
            "mae_r": 1.3436155110806967,
            "entry_type": "classic_38_62",
            "exit_reason": "STOP",
            "score": 18.0,
            "grade": "valid"
          },
          {
            "symbol": "GLD",
            "direction": "SHORT",
            "entry_time": "2025-10-22 13:15:00",
            "exit_time": "2025-10-22 13:30:00",
            "r": -1.030126710000228,
            "pnl": -3489.7500000000828,
            "mfe_r": 1.2056297791113373,
            "mae_r": 1.526113644444746,
            "entry_type": "classic_38_62",
            "exit_reason": "STOP",
            "score": 15.0,
            "grade": "valid"
          },
          {
            "symbol": "GLD",
            "direction": "LONG",
            "entry_time": "2021-07-02 12:15:00",
            "exit_time": "2021-07-02 12:30:00",
            "r": -2.937984283481783,
            "pnl": -3407.250000000042,
            "mfe_r": 3.212196149940017,
            "mae_r": 2.859638035922194,
            "entry_type": "classic_38_62",
            "exit_reason": "STOP",
            "score": 15.0,
            "grade": "valid"
          },
          {
            "symbol": "GLD",
            "direction": "SHORT",
            "entry_time": "2021-07-19 12:30:00",
            "exit_time": "2021-07-19 12:45:00",
            "r": -1.8108921919441894,
            "pnl": -3326.7000000000435,
            "mfe_r": 0.0,
            "mae_r": 3.180669619183994,
            "entry_type": "classic_38_62",
            "exit_reason": "STOP",
            "score": 16.0,
            "grade": "a_plus"
          }
        ],
        "loss_concentration": {
          "loss_count": 59.0,
          "top1_loss_share": 0.0458286981663472,
          "top3_loss_share": 0.11641886952425096,
          "top5_loss_share": 0.18211325918174928
        }
      }
    },
    "oos": {
      "headline": {
        "total_trades": 10.0,
        "net_return_pct": 3.577790000000023,
        "net_return_per_month": 0.6063980498839946,
        "total_pnl_dollars": 3577.7899999999277,
        "pnl_per_trade": 357.7789999999928,
        "profit_factor": 1.7397748990133461,
        "dollar_profit_factor": 1.363389737547728,
        "avg_r": 0.3834032182873563,
        "total_r": 3.834032182873563,
        "r_per_month": 0.6498284244986399,
        "win_rate": 0.5,
        "max_dd_pct": 4.4476431412755115,
        "sharpe": 0.37335488714510534,
        "trades_per_month": 1.6948955916473318,
        "expectancy_frequency": 0.4991455792525672,
        "mfe_capture": 0.2665492721346962,
        "avg_mfe_r": 2.0222488325053662,
        "avg_mae_r": 0.9475344566487186,
        "excellent_trades": 5.0,
        "excellent_trades_per_month": 0.8474477958236659,
        "excellent_rate": 0.5,
        "two_r_plus_rate": 0.4,
        "never_worked_rate": 0.2,
        "false_positive_never_worked_rate": 0.2,
        "low_mfe_loss_rate": 0.4,
        "false_positive_low_mfe_loss_rate": 0.4,
        "half_to_one_r_loss_rate": 0.2,
        "right_then_lost_rate": 0.1,
        "top5_winner_share": 1.0000000000000002,
        "dollar_top5_winner_share": 0.9999999999999999,
        "max_symbol_trade_share": 0.8,
        "dominant_symbol_trade_share": 0.8,
        "gld_trade_count": 8.0,
        "qqq_trade_count": 2.0,
        "gld_excellent_trades": 5.0,
        "qqq_excellent_trades": 0.0,
        "gld_excellent_rate": 0.625,
        "qqq_excellent_rate": 0.0,
        "gld_trade_share": 0.8,
        "max_gld_trade_share": 0.8,
        "qqq_trade_share": 0.2,
        "entry_requests": 15.0,
        "request_fill_rate": 0.6666666666666666,
        "order_terminal_rate": 0.3333333333333333,
        "worst_symbol_avg_r": -1.023500170278813,
        "worst_year_avg_r": 0.056046927397041646,
        "worst_symbol_pnl": -5101.310000000042,
        "worst_symbol_pnl_pct": -5.101310000000042,
        "worst_year_pnl": 866.0399999999845,
        "worst_year_pnl_pct": 0.8660399999999844
      },
      "with_cohorts": {
        "total_trades": 10.0,
        "net_return_pct": 3.577790000000023,
        "net_return_per_month": 0.6063980498839946,
        "total_pnl_dollars": 3577.7899999999277,
        "pnl_per_trade": 357.7789999999928,
        "profit_factor": 1.7397748990133461,
        "dollar_profit_factor": 1.363389737547728,
        "avg_r": 0.3834032182873563,
        "total_r": 3.834032182873563,
        "r_per_month": 0.6498284244986399,
        "win_rate": 0.5,
        "max_dd_pct": 4.4476431412755115,
        "sharpe": 0.37335488714510534,
        "trades_per_month": 1.6948955916473318,
        "expectancy_frequency": 0.4991455792525672,
        "mfe_capture": 0.2665492721346962,
        "avg_mfe_r": 2.0222488325053662,
        "avg_mae_r": 0.9475344566487186,
        "excellent_trades": 5.0,
        "excellent_trades_per_month": 0.8474477958236659,
        "excellent_rate": 0.5,
        "two_r_plus_rate": 0.4,
        "never_worked_rate": 0.2,
        "false_positive_never_worked_rate": 0.2,
        "low_mfe_loss_rate": 0.4,
        "false_positive_low_mfe_loss_rate": 0.4,
        "half_to_one_r_loss_rate": 0.2,
        "right_then_lost_rate": 0.1,
        "top5_winner_share": 1.0000000000000002,
        "dollar_top5_winner_share": 0.9999999999999999,
        "max_symbol_trade_share": 0.8,
        "dominant_symbol_trade_share": 0.8,
        "gld_trade_count": 8.0,
        "qqq_trade_count": 2.0,
        "gld_excellent_trades": 5.0,
        "qqq_excellent_trades": 0.0,
        "gld_excellent_rate": 0.625,
        "qqq_excellent_rate": 0.0,
        "gld_trade_share": 0.8,
        "max_gld_trade_share": 0.8,
        "qqq_trade_share": 0.2,
        "entry_requests": 15.0,
        "request_fill_rate": 0.6666666666666666,
        "order_terminal_rate": 0.3333333333333333,
        "worst_symbol_avg_r": -1.023500170278813,
        "worst_year_avg_r": 0.056046927397041646,
        "worst_symbol_pnl": -5101.310000000042,
        "worst_symbol_pnl_pct": -5.101310000000042,
        "worst_year_pnl": 866.0399999999845,
        "worst_year_pnl_pct": 0.8660399999999844,
        "cohorts": {
          "LONG": {
            "n": 4.0,
            "pnl": -4469.330000000047,
            "avg_r": -0.38069454471785175,
            "win_rate": 0.25,
            "low_mfe_loss_rate": 0.75
          },
          "SHORT": {
            "n": 6.0,
            "pnl": 8047.1199999999735,
            "avg_r": 0.8928017269574949,
            "win_rate": 0.6666666666666666,
            "low_mfe_loss_rate": 0.16666666666666666
          },
          "GLD": {
            "n": 8.0,
            "pnl": 8679.09999999997,
            "avg_r": 0.7351290654288986,
            "win_rate": 0.625,
            "low_mfe_loss_rate": 0.25
          },
          "QQQ": {
            "n": 2.0,
            "pnl": -5101.310000000042,
            "avg_r": -1.023500170278813,
            "win_rate": 0.0,
            "low_mfe_loss_rate": 1.0
          }
        },
        "worst_trades": [
          {
            "symbol": "QQQ",
            "direction": "LONG",
            "entry_time": "2026-04-06 14:00:00",
            "exit_time": "2026-04-06 14:30:00",
            "r": -1.014295586242729,
            "pnl": -2598.9500000000485,
            "mfe_r": 0.0,
            "mae_r": 1.0452401973484464,
            "entry_type": "classic_38_62",
            "exit_reason": "STOP",
            "score": 18.0,
            "grade": "valid"
          },
          {
            "symbol": "QQQ",
            "direction": "LONG",
            "entry_time": "2026-02-18 16:00:00",
            "exit_time": "2026-02-18 18:30:00",
            "r": -1.0327047543148968,
            "pnl": -2502.3599999999938,
            "mfe_r": 0.35516301074320694,
            "mae_r": 1.2020901902078442,
            "entry_type": "classic_38_62",
            "exit_reason": "STOP",
            "score": 18.0,
            "grade": "valid"
          },
          {
            "symbol": "GLD",
            "direction": "LONG",
            "entry_time": "2026-04-01 12:15:00",
            "exit_time": "2026-04-01 12:45:00",
            "r": -1.031247035800739,
            "pnl": -1953.479999999985,
            "mfe_r": 0.5297501896236715,
            "mae_r": 1.4267938440530756,
            "entry_type": "classic_38_62",
            "exit_reason": "STOP",
            "score": 16.0,
            "grade": "valid"
          },
          {
            "symbol": "GLD",
            "direction": "SHORT",
            "entry_time": "2025-11-20 14:45:00",
            "exit_time": "2025-11-20 15:00:00",
            "r": -1.0480649538359772,
            "pnl": -1490.2899999999759,
            "mfe_r": 0.7971198240443075,
            "mae_r": 1.151395301397249,
            "entry_type": "classic_38_62",
            "exit_reason": "STOP",
            "score": 15.0,
            "grade": "valid"
          },
          {
            "symbol": "GLD",
            "direction": "SHORT",
            "entry_time": "2025-11-20 14:15:00",
            "exit_time": "2025-11-20 14:30:00",
            "r": -1.056388769812017,
            "pnl": -1300.5200000000486,
            "mfe_r": 1.091024467182854,
            "mae_r": 1.6798313224878474,
            "entry_type": "classic_38_62",
            "exit_reason": "STOP",
            "score": 16.0,
            "grade": "valid"
          },
          {
            "symbol": "GLD",
            "direction": "SHORT",
            "entry_time": "2026-04-21 18:00:00",
            "exit_time": "2026-04-21 18:45:00",
            "r": 0.6591775982240153,
            "pnl": 1061.0100000000216,
            "mfe_r": 1.4436660997965165,
            "mae_r": 0.20144178136691251,
            "entry_type": "classic_38_62",
            "exit_reason": "STOP",
            "score": 15.0,
            "grade": "valid"
          },
          {
            "symbol": "GLD",
            "direction": "SHORT",
            "entry_time": "2026-03-11 14:15:00",
            "exit_time": "2026-03-11 16:30:00",
            "r": 2.278501008485718,
            "pnl": 2520.0099999999748,
            "mfe_r": 3.5506499816760595,
            "mae_r": 0.8802031467179791,
            "entry_type": "classic_38_62",
            "exit_reason": "STOP",
            "score": 16.0,
            "grade": "valid"
          },
          {
            "symbol": "GLD",
            "direction": "LONG",
            "entry_time": "2026-04-01 13:30:00",
            "exit_time": "2026-04-01 18:00:00",
            "r": 1.555469197486958,
            "pnl": 2585.4599999999805,
            "mfe_r": 3.5203540882253446,
            "mae_r": 0.8664437387686728,
            "entry_type": "classic_38_62",
            "exit_reason": "STOP",
            "score": 16.0,
            "grade": "valid"
          },
          {
            "symbol": "GLD",
            "direction": "SHORT",
            "entry_time": "2026-04-21 19:00:00",
            "exit_time": "2026-04-21 20:15:00",
            "r": 2.2509909728441113,
            "pnl": 3600.059999999992,
            "mfe_r": 3.920491888623842,
            "mae_r": 0.6096207226278163,
            "entry_type": "classic_38_62",
            "exit_reason": "STOP",
            "score": 15.0,
            "grade": "valid"
          },
          {
            "symbol": "GLD",
            "direction": "SHORT",
            "entry_time": "2025-11-20 15:15:00",
            "exit_time": "2025-11-20 19:15:00",
            "r": 2.2725945058391193,
            "pnl": 3656.850000000009,
            "mfe_r": 5.014268775137862,
            "mae_r": 0.41228432151134037,
            "entry_type": "classic_38_62",
            "exit_reason": "STOP",
            "score": 16.0,
            "grade": "valid"
          }
        ],
        "loss_concentration": {
          "loss_count": 5.0,
          "top1_loss_share": 0.26397070772731324,
          "top3_loss_share": 0.7165424148858364,
          "top5_loss_share": 1.0
        }
      }
    }
  },
  "symbol_trade_cohorts": {
    "train_QQQ": {
      "cohort": "split_symbol",
      "split": "train",
      "symbol": "QQQ",
      "trades": 20,
      "pnl_dollars": 44172.69000000057,
      "total_r": 13.081155606866572,
      "avg_r": 0.6540577803433286,
      "median_r": 0.8460531448274335,
      "win_rate": 0.7,
      "profit_factor_r": 3.1371255419164163,
      "avg_mfe_r": 1.8524001039624156,
      "avg_mae_r": 0.6594873713013409,
      "excellent_trades": 14,
      "excellent_rate": 0.7,
      "never_worked_rate": 0.1,
      "low_mfe_loss_rate": 0.3,
      "right_then_lost_rate": 0.0,
      "top1_win_r_share": 0.14612646432539603,
      "top5_win_r_share": 0.5600122447587935
    },
    "oos_QQQ": {
      "cohort": "split_symbol",
      "split": "oos",
      "symbol": "QQQ",
      "trades": 2,
      "pnl_dollars": -5101.310000000042,
      "total_r": -2.047000340557626,
      "avg_r": -1.023500170278813,
      "median_r": -1.023500170278813,
      "win_rate": 0.0,
      "profit_factor_r": 0.0,
      "avg_mfe_r": 0.17758150537160347,
      "avg_mae_r": 1.1236651937781454,
      "excellent_trades": 0,
      "excellent_rate": 0.0,
      "never_worked_rate": 1.0,
      "low_mfe_loss_rate": 1.0,
      "right_then_lost_rate": 0.0,
      "top1_win_r_share": 0.0,
      "top5_win_r_share": 0.0
    },
    "train_GLD": {
      "cohort": "split_symbol",
      "split": "train",
      "symbol": "GLD",
      "trades": 106,
      "pnl_dollars": 52727.399999996844,
      "total_r": 283.3360944836795,
      "avg_r": 2.6729820234309387,
      "median_r": 0.029209366455235135,
      "win_rate": 0.5,
      "profit_factor_r": 4.614890649186412,
      "avg_mfe_r": 8.117338230632397,
      "avg_mae_r": 1.1562606744831916,
      "excellent_trades": 50,
      "excellent_rate": 0.4716981132075472,
      "never_worked_rate": 0.33962264150943394,
      "low_mfe_loss_rate": 0.42452830188679247,
      "right_then_lost_rate": 0.07547169811320754,
      "top1_win_r_share": 0.7563192535700507,
      "top5_win_r_share": 0.8199263369041178
    },
    "oos_GLD": {
      "cohort": "split_symbol",
      "split": "oos",
      "symbol": "GLD",
      "trades": 8,
      "pnl_dollars": 8679.09999999997,
      "total_r": 5.881032523431188,
      "avg_r": 0.7351290654288986,
      "median_r": 1.1073233978554868,
      "win_rate": 0.625,
      "profit_factor_r": 2.8755082115887527,
      "avg_mfe_r": 2.483415664288807,
      "avg_mae_r": 0.9035017723663616,
      "excellent_trades": 5,
      "excellent_rate": 0.625,
      "never_worked_rate": 0.0,
      "low_mfe_loss_rate": 0.25,
      "right_then_lost_rate": 0.125,
      "top1_win_r_share": 0.2526969509913207,
      "top5_win_r_share": 1.0000000000000002
    }
  },
  "rolling_6m_context": {
    "train_window_count": 49,
    "oos_window": {
      "window_start": "OOS",
      "window_end": "OOS",
      "trades": 10,
      "pnl_dollars": 3577.7899999999277,
      "net_return_pct_on_initial": 3.577789999999928,
      "avg_r": 0.3834032182873563,
      "win_rate": 0.5,
      "excellent_trades": 5,
      "excellent_rate": 0.5,
      "low_mfe_loss_rate": 0.4,
      "right_then_lost_rate": 0.1,
      "qqq_trades": 2,
      "qqq_pnl_dollars": -5101.310000000042,
      "qqq_avg_r": -1.023500170278813,
      "qqq_excellent_trades": 0,
      "gld_trades": 8,
      "gld_pnl_dollars": 8679.09999999997,
      "gld_avg_r": 0.7351290654288986,
      "gld_excellent_trades": 5
    },
    "train_net_return_pct_percentiles": {
      "p10": -1.6590940000002368,
      "p25": 5.746619999999885,
      "p50": 10.496860000000211,
      "p75": 21.2518399999998,
      "p90": 28.4513879999994
    },
    "train_total_trades_percentiles": {
      "p10": 8.0,
      "p25": 10.0,
      "p50": 13.0,
      "p75": 18.0,
      "p90": 19.0
    },
    "train_qqq_trades_percentiles": {
      "p10": 0.0,
      "p25": 1.0,
      "p50": 2.0,
      "p75": 4.0,
      "p90": 5.0
    },
    "train_gld_trades_percentiles": {
      "p10": 6.800000000000001,
      "p25": 8.0,
      "p50": 12.0,
      "p75": 15.0,
      "p90": 16.0
    },
    "oos_net_return_pct_rank_vs_train_6m": 0.20408163265306123,
    "oos_trade_count_rank_vs_train_6m": 0.2653061224489796
  },
  "shadow_setup_context": {
    "train_QQQ": {
      "shadow_bars": 74047,
      "entry_ready_bars": 103,
      "entry_ready_rate": 0.0013910084135751617,
      "regime_reject_rate": 0.2065444920118303,
      "session_reject_rate": 0.7825030048482721,
      "pullback_reject_rate": 0.0020662552162815507,
      "confirmation_reject_rate": 0.00021607897686604454,
      "top_first_failures": [
        {
          "reason": "session_filter",
          "bars": 57942
        },
        {
          "reason": "regime_ma_rsi_conflict",
          "bars": 14174
        },
        {
          "reason": "regime_long_trend_quality",
          "bars": 523
        },
        {
          "reason": "direction_shorts_disabled",
          "bars": 491
        },
        {
          "reason": "regime_extended_from_value",
          "bars": 415
        },
        {
          "reason": "regime_short_trend_quality",
          "bars": 182
        },
        {
          "reason": "pullback_none",
          "bars": 119
        },
        {
          "reason": "entry_ready",
          "bars": 92
        }
      ]
    },
    "train_GLD": {
      "shadow_bars": 73527,
      "entry_ready_bars": 347,
      "entry_ready_rate": 0.004719354794837271,
      "regime_reject_rate": 0.3495858664164185,
      "session_reject_rate": 0.6265725515796918,
      "pullback_reject_rate": 0.015055693826757517,
      "confirmation_reject_rate": 0.00228487494389816,
      "top_first_failures": [
        {
          "reason": "session_filter",
          "bars": 46070
        },
        {
          "reason": "regime_ma_rsi_conflict",
          "bars": 23325
        },
        {
          "reason": "regime_extended_from_value",
          "bars": 1006
        },
        {
          "reason": "regime_long_trend_quality",
          "bars": 861
        },
        {
          "reason": "pullback_none",
          "bars": 543
        },
        {
          "reason": "regime_short_trend_quality",
          "bars": 512
        },
        {
          "reason": "pullback_none",
          "bars": 360
        },
        {
          "reason": "entry_ready",
          "bars": 159
        }
      ]
    },
    "oos_QQQ": {
      "shadow_bars": 7905,
      "entry_ready_bars": 17,
      "entry_ready_rate": 0.002150537634408602,
      "regime_reject_rate": 0.1911448450347881,
      "session_reject_rate": 0.7879822896900696,
      "pullback_reject_rate": 0.00683111954459203,
      "confirmation_reject_rate": 0.0008855154965211891,
      "top_first_failures": [
        {
          "reason": "session_filter",
          "bars": 6229
        },
        {
          "reason": "regime_ma_rsi_conflict",
          "bars": 1387
        },
        {
          "reason": "regime_long_trend_quality",
          "bars": 82
        },
        {
          "reason": "direction_shorts_disabled",
          "bars": 67
        },
        {
          "reason": "pullback_none",
          "bars": 40
        },
        {
          "reason": "regime_short_trend_quality",
          "bars": 28
        },
        {
          "reason": "direction_shorts_disabled",
          "bars": 20
        },
        {
          "reason": "regime_extended_from_value",
          "bars": 14
        }
      ]
    },
    "oos_GLD": {
      "shadow_bars": 7385,
      "entry_ready_bars": 22,
      "entry_ready_rate": 0.002979011509817197,
      "regime_reject_rate": 0.34434664861205144,
      "session_reject_rate": 0.6343940419769803,
      "pullback_reject_rate": 0.013947190250507786,
      "confirmation_reject_rate": 0.0013540961408259986,
      "top_first_failures": [
        {
          "reason": "session_filter",
          "bars": 4685
        },
        {
          "reason": "regime_ma_rsi_conflict",
          "bars": 2284
        },
        {
          "reason": "regime_long_trend_quality",
          "bars": 130
        },
        {
          "reason": "regime_extended_from_value",
          "bars": 105
        },
        {
          "reason": "pullback_none",
          "bars": 73
        },
        {
          "reason": "pullback_none",
          "bars": 28
        },
        {
          "reason": "regime_short_trend_quality",
          "bars": 24
        },
        {
          "reason": "daily_room",
          "bars": 17
        }
      ]
    }
  },
  "interpretation_flags": {
    "train_r_is_top_winner_concentrated": true,
    "oos_sample_is_small": true,
    "qqq_oos_sample_is_too_small_for_decisive_rejection": true,
    "prob_zero_qqq_excellent_given_train_rate": 0.09000000000000002,
    "qqq_oos_negative_avg_r": true,
    "gld_oos_positive_avg_r": true,
    "asset_context_is_stubbed_in_code": true,
    "news_filter_is_stubbed_in_code": true,
    "score_gets_asset_context_credit_unconditionally": true,
    "shadow_qqq_oos_entry_ready_rate": 0.002150537634408602,
    "shadow_gld_oos_entry_ready_rate": 0.002979011509817197
  }
}